gp2y0e02b.py
circuitpython_gp2y0e02b-0.0.1.dist-info/LICENSE
circuitpython_gp2y0e02b-0.0.1.dist-info/METADATA
circuitpython_gp2y0e02b-0.0.1.dist-info/WHEEL
circuitpython_gp2y0e02b-0.0.1.dist-info/top_level.txt
circuitpython_gp2y0e02b-0.0.1.dist-info/RECORD
