Metadata-Version: 2.1
Name: circuitpython-gp2y0e02b
Version: 0.0.1
Summary: Driver for the GP2Y0E02B distance sensor
Author-email: "Jose D. Montoya" <gpy@mailmeto.mozmail.com>
License: MIT
Project-URL: Homepage, https://github.com/jposada202020/CircuitPython_GP2Y0E02B
Keywords: adafruit,blinka,circuitpython,micropython,gp2y0e02b,distance,GP2Y0E02B,sensor,measure,python
Classifier: Intended Audience :: Developers
Classifier: Topic :: Software Development :: Libraries
Classifier: Topic :: Software Development :: Embedded Systems
Classifier: Topic :: System :: Hardware
Classifier: License :: OSI Approved :: MIT License
Classifier: Programming Language :: Python :: 3
License-File: LICENSE
Requires-Dist: Adafruit-Blinka
Requires-Dist: adafruit-circuitpython-busdevice
Requires-Dist: adafruit-circuitpython-register
Provides-Extra: optional
